readings.py
FitHome_readings-0.0.2.dist-info/LICENCE.txt
FitHome_readings-0.0.2.dist-info/METADATA
FitHome_readings-0.0.2.dist-info/WHEEL
FitHome_readings-0.0.2.dist-info/top_level.txt
FitHome_readings-0.0.2.dist-info/RECORD
