Metadata-Version: 2.1
Name: FitHome-readings
Version: 0.0.2
Summary: Get active power readings from the mongo db and put into a pandas DataFrame.
Home-page: UNKNOWN
License: UNKNOWN
Platform: UNKNOWN
Classifier: Programming Language :: Python :: 3
Classifier: License :: OSI Approved :: MIT License
Classifier: Operating System :: OS Independent
Requires-Dist: pymongo (==3.4.0)
Requires-Dist: pandas (==1.0.1)
